csv_explorer_util/__init__.py
csv_explorer_util-0.1.0.dist-info/METADATA
csv_explorer_util-0.1.0.dist-info/WHEEL
csv_explorer_util-0.1.0.dist-info/RECORD
