Metadata-Version: 2.1
Name: csv-explorer-util
Version: 0.1.0
Summary: 
Author: Andrew Matte
Author-email: andrew.matte@gmail.com
Requires-Python: >=3.12,<4.0
Classifier: Programming Language :: Python :: 3
Classifier: Programming Language :: Python :: 3.12
Classifier: Programming Language :: Python :: 3.13
Requires-Dist: inquirer (>=3.4.0,<4.0.0)
Requires-Dist: rich (>=13.7.1,<14.0.0)
